MANIFEST.in
requirements.txt
setup.cfg
setup.py
openytapi.egg-info/PKG-INFO
openytapi.egg-info/SOURCES.txt
openytapi.egg-info/dependency_links.txt
openytapi.egg-info/requires.txt
openytapi.egg-info/top_level.txt
youtube/__init__.py
youtube/api.py
youtube/baseelement.py
youtube/baseparser.py
youtube/cache.py
youtube/channelsearchparser.py
youtube/errors.py
youtube/http_fetcher.py
youtube/playlist.py
youtube/playlistpageparser.py
youtube/playlistsearchparser.py
youtube/search.py
youtube/signatures.py
youtube/tools.py
youtube/video.py
youtube/videopageparser.py
youtube/videosearchparser.py