Metadata-Version: 1.1
Name: openytapi
Version: 2.4.1
Summary: Open YouTube API library
Home-page: https://github.com/Glenpl/openytapi
Author: Glenpl/Jakub Molinski
Author-email: kubamolinski@gmail.com
License: MIT
Download-URL: https://github.com/Glenpl/openytapi/tarball/2.4.1
Keywords: open youtube api
Platform: UNKNOWN
Classifier: Intended Audience :: Developers
Classifier: License :: OSI Approved :: MIT License
Classifier: Programming Language :: Python
Classifier: Programming Language :: Python :: 3 :: Only
Classifier: Programming Language :: Python :: 3
Classifier: Programming Language :: Python :: 3.4
Classifier: Programming Language :: Python :: 3.5
